{"devicePlatform":"","logFolder":"C:\\Users\\slk\\Katalon Studio\\Demo\\Reports\\VAR\\20180725_111834","runData":{"hostName":"slk - WSLK1FFTRFW-01.SLKSOFT.COM","os":"Windows 7 64bit","katalonVersion":"5.5.0.1","browser":"Chrome 67.0.3396.99","hostAddress":"192.168.56.1","sessionId":"6e487e4df605bcdbf0883d67a33f7f3c","seleniumVersion":"3.7.1","proxyInformation":"ProxyInformation{proxyOption\u003dNO_PROXY, proxyServerType\u003dHTTP, password\u003d, proxyServerAddress\u003d, proxyServerPort\u003d0}","platform":"Windows 7"},"type":"TEST_SUITE","name":"VAR","id":"Test Suites/VAR","source":"","message":"Test Cases/DAY2/Test VAR_global","description":"","startTime":1532497715431,"endTime":1532497732182,"childRecords":[{"isOptional":false,"type":"TEST_CASE","name":"Test Cases/DAY2/Test VAR","id":"Test Cases/DAY2/Test VAR","source":"C:\\\\Users\\\\slk\\\\Katalon Studio\\\\Demo\\\\Test Cases\\\\DAY2\\\\Test VAR.tc","message":"Test Cases/DAY2/Test VAR","description":"","startTime":1532497715699,"endTime":1532497724450,"childRecords":[{"testStatus":{"stackTrace":"","statusValue":"INFO"},"type":"MESSAGE","name":"","message":"Evaluating variables for test case","startTime":1532497715732,"endTime":0,"childRecords":[],"interuppted":false},{"testStatus":{"stackTrace":"","statusValue":"INFO"},"type":"MESSAGE","name":"","message":"Variable \u0027url\u0027 is set to https://opensource-demo.orangehrmlive.com/ as default","startTime":1532497715755,"endTime":0,"childRecords":[],"interuppted":false},{"testStatus":{"stackTrace":"","statusValue":"INFO"},"type":"MESSAGE","name":"","message":"Variable \u0027username\u0027 is set to Admin as default","startTime":1532497715788,"endTime":0,"childRecords":[],"interuppted":false},{"testStatus":{"stackTrace":"","statusValue":"INFO"},"type":"MESSAGE","name":"","message":"Variable \u0027password\u0027 is set to admin123 as default","startTime":1532497715788,"endTime":0,"childRecords":[],"interuppted":false},{"index":1,"isIgnoredIfFailed":false,"type":"TEST_STEP","name":"openBrowser","message":"Browser is opened with url: \u0027\u0027","description":"","startTime":1532497716013,"endTime":1532497718780,"childRecords":[{"testStatus":{"stackTrace":"","statusValue":"PASSED"},"type":"MESSAGE","name":"","message":"Browser is opened with url: \u0027\u0027","startTime":1532497718779,"endTime":0,"childRecords":[],"interuppted":false}],"interuppted":false},{"index":2,"isIgnoredIfFailed":false,"type":"TEST_STEP","name":"navigateToUrl","message":"Navigate to \u0027https://opensource-demo.orangehrmlive.com/\u0027 successfully","description":"","startTime":1532497718780,"endTime":1532497722824,"childRecords":[{"testStatus":{"stackTrace":"","statusValue":"PASSED"},"type":"MESSAGE","name":"","message":"Navigate to \u0027https://opensource-demo.orangehrmlive.com/\u0027 successfully","startTime":1532497722823,"endTime":0,"childRecords":[],"interuppted":false}],"interuppted":false},{"index":3,"isIgnoredIfFailed":false,"type":"TEST_STEP","name":"setText","message":"Text \u0027AdminREG\u0027 is set on object \u0027Object Repository/variable test/Page_OrangeHRM/input_txtUsername\u0027","description":"","startTime":1532497722825,"endTime":1532497722984,"childRecords":[{"testStatus":{"stackTrace":"","statusValue":"PASSED"},"type":"MESSAGE","name":"","message":"Text \u0027AdminREG\u0027 is set on object \u0027Object Repository/variable test/Page_OrangeHRM/input_txtUsername\u0027","startTime":1532497722984,"endTime":0,"childRecords":[],"interuppted":false}],"interuppted":false},{"index":4,"isIgnoredIfFailed":false,"type":"TEST_STEP","name":"setText","message":"Text \u0027admin123\u0027 is set on object \u0027Object Repository/variable test/Page_OrangeHRM/input_txtPassword\u0027","description":"","startTime":1532497722984,"endTime":1532497723067,"childRecords":[{"testStatus":{"stackTrace":"","statusValue":"PASSED"},"type":"MESSAGE","name":"","message":"Text \u0027admin123\u0027 is set on object \u0027Object Repository/variable test/Page_OrangeHRM/input_txtPassword\u0027","startTime":1532497723067,"endTime":0,"childRecords":[],"interuppted":false}],"interuppted":false},{"index":5,"isIgnoredIfFailed":false,"type":"TEST_STEP","name":"click","message":"Object: \u0027Object Repository/variable test/Page_OrangeHRM/input_Submit\u0027 is clicked on","description":"","startTime":1532497723067,"endTime":1532497723786,"childRecords":[{"testStatus":{"stackTrace":"","statusValue":"PASSED"},"type":"MESSAGE","name":"","message":"Object: \u0027Object Repository/variable test/Page_OrangeHRM/input_Submit\u0027 is clicked on","startTime":1532497723785,"endTime":0,"childRecords":[],"interuppted":false}],"interuppted":false},{"index":6,"isIgnoredIfFailed":false,"type":"TEST_STEP","name":"closeBrowser","message":"Browser is closed","description":"","startTime":1532497723787,"endTime":1532497724434,"childRecords":[{"testStatus":{"stackTrace":"","statusValue":"PASSED"},"type":"MESSAGE","name":"","message":"Browser is closed","startTime":1532497724433,"endTime":0,"childRecords":[],"interuppted":false}],"interuppted":false},{"testStatus":{"stackTrace":"","statusValue":"PASSED"},"type":"MESSAGE","name":"","message":"Test Cases/DAY2/Test VAR","startTime":1532497724434,"endTime":0,"childRecords":[],"interuppted":false}],"interuppted":false},{"isOptional":false,"type":"TEST_CASE","name":"Test Cases/DAY2/Test VAR_global","id":"Test Cases/DAY2/Test VAR_global","source":"C:\\\\Users\\\\slk\\\\Katalon Studio\\\\Demo\\\\Test Cases\\\\DAY2\\\\Test VAR_global.tc","message":"Test Cases/DAY2/Test VAR_global","description":"","startTime":1532497724465,"endTime":1532497732119,"childRecords":[{"testStatus":{"stackTrace":"","statusValue":"INFO"},"type":"MESSAGE","name":"","message":"Evaluating variables for test case","startTime":1532497724466,"endTime":0,"childRecords":[],"interuppted":false},{"testStatus":{"stackTrace":"","statusValue":"INFO"},"type":"MESSAGE","name":"","message":"Variable \u0027url\u0027 is set to https://opensource-demo.orangehrmlive.com/ as default","startTime":1532497724466,"endTime":0,"childRecords":[],"interuppted":false},{"testStatus":{"stackTrace":"","statusValue":"INFO"},"type":"MESSAGE","name":"","message":"Variable \u0027username\u0027 is set to Admin as default","startTime":1532497724497,"endTime":0,"childRecords":[],"interuppted":false},{"testStatus":{"stackTrace":"","statusValue":"INFO"},"type":"MESSAGE","name":"","message":"Variable \u0027password\u0027 is set to admin123 as default","startTime":1532497724497,"endTime":0,"childRecords":[],"interuppted":false},{"index":1,"isIgnoredIfFailed":false,"type":"TEST_STEP","name":"openBrowser","message":"Browser is opened with url: \u0027\u0027","description":"","startTime":1532497724612,"endTime":1532497726557,"childRecords":[{"testStatus":{"stackTrace":"","statusValue":"PASSED"},"type":"MESSAGE","name":"","message":"Browser is opened with url: \u0027\u0027","startTime":1532497726556,"endTime":0,"childRecords":[],"interuppted":false}],"interuppted":false},{"index":2,"isIgnoredIfFailed":false,"type":"TEST_STEP","name":"navigateToUrl","message":"Navigate to \u0027https://opensource-demo.orangehrmlive.com/\u0027 successfully","description":"","startTime":1532497726557,"endTime":1532497730475,"childRecords":[{"testStatus":{"stackTrace":"","statusValue":"PASSED"},"type":"MESSAGE","name":"","message":"Navigate to \u0027https://opensource-demo.orangehrmlive.com/\u0027 successfully","startTime":1532497730474,"endTime":0,"childRecords":[],"interuppted":false}],"interuppted":false},{"index":3,"isIgnoredIfFailed":false,"type":"TEST_STEP","name":"setText","message":"Text \u0027AdminREG\u0027 is set on object \u0027Object Repository/variable test/Page_OrangeHRM/input_txtUsername\u0027","description":"","startTime":1532497730475,"endTime":1532497730599,"childRecords":[{"testStatus":{"stackTrace":"","statusValue":"PASSED"},"type":"MESSAGE","name":"","message":"Text \u0027AdminREG\u0027 is set on object \u0027Object Repository/variable test/Page_OrangeHRM/input_txtUsername\u0027","startTime":1532497730598,"endTime":0,"childRecords":[],"interuppted":false}],"interuppted":false},{"index":4,"isIgnoredIfFailed":false,"type":"TEST_STEP","name":"setText","message":"Text \u0027admin123\u0027 is set on object \u0027Object Repository/variable test/Page_OrangeHRM/input_txtPassword\u0027","description":"","startTime":1532497730599,"endTime":1532497730697,"childRecords":[{"testStatus":{"stackTrace":"","statusValue":"PASSED"},"type":"MESSAGE","name":"","message":"Text \u0027admin123\u0027 is set on object \u0027Object Repository/variable test/Page_OrangeHRM/input_txtPassword\u0027","startTime":1532497730696,"endTime":0,"childRecords":[],"interuppted":false}],"interuppted":false},{"index":5,"isIgnoredIfFailed":false,"type":"TEST_STEP","name":"click","message":"Object: \u0027Object Repository/variable test/Page_OrangeHRM/input_Submit\u0027 is clicked on","description":"","startTime":1532497730697,"endTime":1532497731492,"childRecords":[{"testStatus":{"stackTrace":"","statusValue":"PASSED"},"type":"MESSAGE","name":"","message":"Object: \u0027Object Repository/variable test/Page_OrangeHRM/input_Submit\u0027 is clicked on","startTime":1532497731490,"endTime":0,"childRecords":[],"interuppted":false}],"interuppted":false},{"index":6,"isIgnoredIfFailed":false,"type":"TEST_STEP","name":"closeBrowser","message":"Browser is closed","description":"","startTime":1532497731492,"endTime":1532497732118,"childRecords":[{"testStatus":{"stackTrace":"","statusValue":"PASSED"},"type":"MESSAGE","name":"","message":"Browser is closed","startTime":1532497732117,"endTime":0,"childRecords":[],"interuppted":false}],"interuppted":false},{"testStatus":{"stackTrace":"","statusValue":"PASSED"},"type":"MESSAGE","name":"","message":"Test Cases/DAY2/Test VAR_global","startTime":1532497732118,"endTime":0,"childRecords":[],"interuppted":false}],"interuppted":false}],"interuppted":false}